pme/__init__.py
pme/inversion.py
pme/model.py
pme/convert/__init__.py
pme/convert/pme_to_npz.py
pme/data/__init__.py
pme/data/create_test_set.py
pme/data/create_test_set_pymilne_comparison.py
pme/data/crop_psf.py
pme/data/download.py
pme/data/download_hmi.py
pme/data/muram_prep.py
pme/data/muram_sunspot_prep.py
pme/evaluation/__init__.py
pme/evaluation/compare_muram.py
pme/evaluation/compute_uncertainty.py
pme/evaluation/loader.py
pme/evaluation/parameters.py
pme/evaluation/util.py
pme/evaluation/video.py
pme/evaluation/hinode/__init__.py
pme/evaluation/hinode/compare_hinode.py
pme/evaluation/hinode/load_time_series.py
pme/evaluation/muram/__init__.py
pme/evaluation/muram/compare_muram.py
pme/evaluation/test_set/__init__.py
pme/evaluation/test_set/compare_noise.py
pme/train/__init__.py
pme/train/atomic_functions.py
pme/train/data_loader.py
pme/train/me_atmosphere.py
pme/train/me_equations.py
pme/train/me_module.py
pme/train/profile_functions.py
pme/train/psf.py
pme/train/util.py
pinn_me-0.1.1.dist-info/LICENSE
pinn_me-0.1.1.dist-info/METADATA
pinn_me-0.1.1.dist-info/WHEEL
pinn_me-0.1.1.dist-info/entry_points.txt
pinn_me-0.1.1.dist-info/top_level.txt
pinn_me-0.1.1.dist-info/RECORD
