Metadata-Version: 2.1
Name: pinn-me
Version: 0.1.1
Summary: Spectropolarimetric Milne-Eddington Inversions with Physics-Informed Neural Networks
Home-page: https://github.com/RobertJaro/pinn-me
Author: Robert Jarolim, Momchil Molnar
Author-email: 
License: GNU GENERAL PUBLIC LICENSE
License-File: LICENSE
Requires-Dist: torch >=1.8
Requires-Dist: sunpy[all] >=3.0
Requires-Dist: tqdm
Requires-Dist: wandb >=0.13
Requires-Dist: lightning ==1.9.3
Requires-Dist: pytorch-lightning ==1.9.3
